[
    {
        "title": "ข้าวต้มปลากระพง กระดูกหมู ร้านข้าวต้มเป็ด ข้าวต้มแห้งคู้บอน36 เปิด18.30-23.00น.#เฮียพี",
        "description": "วิดีโอสั้นเกี่ยวกับ Flutter",
        "channelProfileUrl": "https://shotstack-assets.s3.ap-southeast-2.amazonaws.com/examples/picture-in-picture/commentary.mp4",
        "channel": "เฮียพี",
        "upload_date": "2025-01-28",
        "duration":"0.15",
        "views": "7.5K",
        "likes": "380090",
        "comments": "62",
        "video_url": "https://r3---sn-30a7rned.googlevideo.com/videoplayback?expire=1740315847&ei=Z8i6Z4f4MZOM6dsP4N-w8AQ&ip=176.6.140.199&id=o-AGjNZSFmywoy7Cxgx3ppvgwFBrpxbrslJr45JHGrs_Gs&itag=18&source=youtube&requiressl=yes&xpc=EgVo2aDSNQ%3D%3D&rms=au%2Cau&bui=AUWDL3wEsQxjXHKl7xyVHID4FXKk1xRxHP8wPPmhXxy_xi-tczmCc5DR24SDJMS0zHWdRAJ47zHfV8_Z&spc=RjZbScrr0Gr3ENnuSG0Eie4Zpd_2XVT7yVn84Yyf0CEI0y6hAj3P&vprv=1&svpuc=1&mime=video%2Fmp4&ns=w13VqMeBsEH5RfIRKk0TYksQ&rqh=1&gir=yes&clen=5308442&ratebypass=yes&dur=74.240&lmt=1731348828308858&fexp=51326932%2C51355912&c=WEB&sefc=1&txp=5430434&n=SGfEih5jfI-iDg&sparams=expire%2Cei%2Cip%2Cid%2Citag%2Csource%2Crequiressl%2Cxpc%2Cbui%2Cspc%2Cvprv%2Csvpuc%2Cmime%2Cns%2Crqh%2Cgir%2Cclen%2Cratebypass%2Cdur%2Clmt&sig=AJfQdSswRAIgLEwES1U0IMJq5y_Ytn5dONtpX16nOdHiiv6I0eR1guoCIGDgTyspkYObAhETC4SoNj0qkQlTFMq8fSyoR5hNCfUN&pot=MnTEP2dSqb_7SMQDuT6I_xd9RG6TL0YIIwG27kRpWfkmwIv3PrCNxSMjXONRuURUn8z7_kMqJ51kAlesI4qmZqtTnY5WuhKStQhK4tCxJaykUPf66LXOU_ERcYl-UbcYfA7Zhccdac8wy8XVWF5g-RU5JaaWdQ==&cms_redirect=yes&met=1740294250,&mh=4h&mip=171.6.27.161&mm=31&mn=sn-30a7rned&ms=au&mt=1740293819&mv=m&mvi=3&pl=24&lsparams=met,mh,mip,mm,mn,ms,mv,mvi,pl,rms&lsig=AGluJ3MwRQIhAIe5ICVzc-Vie3TZQVvQA3rnMYEtW83MPBIxCZz3xVhmAiB_cTxNjXDsYXIX5WRdl-0HgB9FiV2c6dugazNLwk1JXQ%3D%3D",
        "tags": ["#เฮียพี", "Shorts", "Coding"]
    },
    {
        "title": "ข้าวต้มปลากระพง กระดูกหมู ร้านข้าวต้มเป็ด ข้าวต้มแห้งคู้บอน36 เปิด18.30-23.00น.#เฮียพี",
        "description": "วิดีโอสั้นเกี่ยวกับ Flutter",
        "channelProfileUrl": "https://yt3.ggpht.com/ytc/AMLnZu9IIpSHbPejMDtBrI288dyVEXrhshrpwAkvVHIfow=s176-c-k-c0x00ffffff-no-rj",
        "channel": "เฮียผา",
        "upload_date": "2025-01-28",
        "duration":"0.15",
        "views": "5.5K",
        "likes": "380090",
        "comments": "800",
        "video_url": "http://commondatastorage.googleapis.com/gtv-videos-bucket/sample/ElephantsDream.mp4",
        "tags": ["#เฮียพี", "Shorts", "Coding"]
    },
    {
        "title": "ข้าวต้มปลากระพง กระดูกหมู ร้านข้าวต้มเป็ด ข้าวต้มแห้งคู้บอน36 เปิด18.30-23.00น.#เฮียพี",
        "description": "วิดีโอสั้นเกี่ยวกับ Flutter",
        "channelProfileUrl": "https://yt3.ggpht.com/ytc/AMLnZu9IIpSHbPejMDtBrI288dyVEXrhshrpwAkvVHIfow=s176-c-k-c0x00ffffff-no-rj",
        "channel": "เฮียพี",
        "upload_date": "2025-01-28",
        "duration":"0.15",
        "views": "7.5K",
        "likes": "380090",
        "comments": "62",
        "video_url": "http://commondatastorage.googleapis.com/gtv-videos-bucket/sample/ElephantsDream.mp4",
        "tags": ["#เฮียพี", "Shorts", "Coding"]
    }
]